mprpc
