Metadata-Version: 1.1
Name: mprpc
Version: 0.1.15
Summary: A fast MessagePack RPC library
Home-page: http://github.com/studio-ousia/mprpc
Author: Studio Ousia
Author-email: ikuya@ousia.jp
License: Copyright 2013 Studio Ousia
